{
  "project_info": {
    "project_number": "528608210144",
    "project_id": "fixradar-77067",
    "storage_bucket": "fixradar-77067.firebasestorage.app"
  },
  "client": [
    {
      "client_info": {
        "mobilesdk_app_id": "1:528608210144:android:f4b811935189d7be893485",
        "android_client_info": {
          "package_name": "com.venturesflstudio.fix_radar"
        }
      },
      "oauth_client": [
        {
          "client_id": "528608210144-30nho2nd4dpojtbe9ec94uncdu1jf0mv.apps.googleusercontent.com",
          "client_type": 1,
          "android_info": {
            "package_name": "com.venturesflstudio.fix_radar",
            "certificate_hash": "a4154153aaf2e4a1356e539b1ad0e5f38292c082"
          }
        },
        {
          "client_id": "528608210144-da51k5jg6oa6bofodijdghucoknuln6i.apps.googleusercontent.com",
          "client_type": 1,
          "android_info": {
            "package_name": "com.venturesflstudio.fix_radar",
            "certificate_hash": "5f8714fc2a93819f2f4cbff526bb496a4cb96b06"
          }
        },
        {
          "client_id": "528608210144-cajos5fejrd64hjfscv8kq6k9qmo2baa.apps.googleusercontent.com",
          "client_type": 3
        }
      ],
      "api_key": [
        {
          "current_key": "AIzaSyDWS9722OGGyNTtDVaL4LJSQsuvAXKxBPI"
        }
      ],
      "services": {
        "appinvite_service": {
          "other_platform_oauth_client": [
            {
              "client_id": "528608210144-cajos5fejrd64hjfscv8kq6k9qmo2baa.apps.googleusercontent.com",
              "client_type": 3
            },
            {
              "client_id": "528608210144-4nnmq9kqont8b0bjs2s2v6r9fnhu54vp.apps.googleusercontent.com",
              "client_type": 2,
              "ios_info": {
                "bundle_id": "com.venturesflstudio.fixRadar"
              }
            }
          ]
        }
      }
    }
  ],
  "configuration_version": "1"
}